README.md
setup.cfg
setup.py
dsnd_distributions_tools/Binomialdistribution.py
dsnd_distributions_tools/Gaussiandistribution.py
dsnd_distributions_tools/Generaldistribution.py
dsnd_distributions_tools/__init__.py
dsnd_distributions_tools.egg-info/PKG-INFO
dsnd_distributions_tools.egg-info/SOURCES.txt
dsnd_distributions_tools.egg-info/dependency_links.txt
dsnd_distributions_tools.egg-info/not-zip-safe
dsnd_distributions_tools.egg-info/top_level.txt