Metadata-Version: 1.0
Name: dsnd-distributions-tools
Version: 0.1
Summary: Gaussian and Binomial distributions
Home-page: UNKNOWN
Author: Denys Lazarenko
Author-email: denis.lazarenko@gmail.com
License: UNKNOWN
Keywords: gaussian,binomial
Platform: UNKNOWN
